{
  "color": {
    "$type": "color",
    "alias": {
      "aqua": {
        "05": {
          "$description": "Alias for #F7FEFF.",
          "$value": "#F7FEFF"
        },
        "10": {
          "$description": "Alias for #E9F4F6.",
          "$value": "#E9F4F6"
        },
        "20": {
          "$description": "Alias for #C5E1E7.",
          "$value": "#C5E1E7"
        },
        "30": {
          "$description": "Alias for #7DBBC9.",
          "$value": "#7DBBC9"
        },
        "40": {
          "$description": "Alias for #428D9E.",
          "$value": "#428D9E"
        },
        "50": {
          "$description": "Alias for #336D7A.",
          "$value": "#336D7A"
        },
        "60": {
          "$description": "Alias for #087D96.",
          "$value": "#087D96"
        },
        "70": {
          "$description": "Alias for #244D56.",
          "$value": "#244D56"
        },
        "80": {
          "$description": "Alias for #152D32.",
          "$value": "#152D32"
        },
        "90": {
          "$description": "Alias for #003946.",
          "$value": "#003946"
        },
        "100": {
          "$description": "Alias for #102023.",
          "$value": "#102023"
        }
      },
      "black": {
        "$description": "Alias for #000000.",
        "$value": "#000000"
      },
      "blue": {
        "05": {
          "$description": "Alias for #F7F9FC.",
          "$value": "#F7F9FC"
        },
        "10": {
          "$description": "Alias for #D7E3EF.",
          "$value": "#D7E3EF"
        },
        "20": {
          "$description": "Alias for #BCD1E8.",
          "$value": "#BCD1E8"
        },
        "30": {
          "$description": "Alias for #95B3D4.",
          "$value": "#95B3D4"
        },
        "40": {
          "$description": "Alias for #759DC7.",
          "$value": "#759DC7"
        },
        "50": {
          "$description": "Alias for #5485BA.",
          "$value": "#5485BA"
        },
        "60": {
          "$description": "Alias for #406E9F.",
          "$value": "#406E9F"
        },
        "70": {
          "$description": "Alias for #33587F.",
          "$value": "#33587F"
        },
        "80": {
          "$description": "Alias for #26415E.",
          "$value": "#26415E"
        },
        "90": {
          "$description": "Alias for #192A3D.",
          "$value": "#192A3D"
        },
        "100": {
          "$description": "Alias for #001933.",
          "$value": "#001933"
        }
      },
      "electric_lime": {
        "05": {
          "$description": "Alias for #FEFFF8.",
          "$value": "#FEFFF8"
        },
        "10": {
          "$description": "Alias for #FCFFEE.",
          "$value": "#FCFFEE"
        },
        "20": {
          "$description": "Alias for #F2FFBE.",
          "$value": "#F2FFBE"
        },
        "30": {
          "$description": "Alias for #E9FF8F.",
          "$value": "#E9FF8F"
        },
        "40": {
          "$description": "Alias for #DFFF5F.",
          "$value": "#DFFF5F"
        },
        "50": {
          "$description": "Alias for #D6FF30.",
          "$value": "#D6FF30"
        },
        "60": {
          "$description": "Alias for #CCFF00.",
          "$value": "#CCFF00"
        },
        "70": {
          "$description": "Alias for #A3CC00.",
          "$value": "#A3CC00"
        },
        "80": {
          "$description": "Alias for #7A9900.",
          "$value": "#7A9900"
        },
        "90": {
          "$description": "Alias for #526600.",
          "$value": "#526600"
        },
        "100": {
          "$description": "Alias for #293300.",
          "$value": "#293300"
        }
      },
      "gray": {
        "05": {
          "$description": "Alias for #F9FBF9.",
          "$value": "#F9FBF9"
        },
        "10": {
          "$description": "Alias for #F1F3F1.",
          "$value": "#F1F3F1"
        },
        "20": {
          "$description": "Alias for #E3E8E3.",
          "$value": "#E3E8E3"
        },
        "30": {
          "$description": "Alias for #D2D7D2.",
          "$value": "#D2D7D2"
        },
        "40": {
          "$description": "Alias for #9DA99D.",
          "$value": "#9DA99D"
        },
        "50": {
          "$description": "Alias for #697769.",
          "$value": "#697769"
        },
        "60": {
          "$description": "Alias for #4E594E.",
          "$value": "#4E594E"
        },
        "70": {
          "$description": "Alias for #3D443D.",
          "$value": "#3D443D"
        },
        "80": {
          "$description": "Alias for #242824.",
          "$value": "#242824"
        },
        "90": {
          "$description": "Alias for #0D0F0D.",
          "$value": "#0D0F0D"
        },
        "100": {
          "$description": "Alias for #070807.",
          "$value": "#070807"
        }
      },
      "green": {
        "05": {
          "$description": "Alias for #F7FCFB.",
          "$value": "#F7FCFB"
        },
        "10": {
          "$description": "Alias for #ECFFFB.",
          "$value": "#ECFFFB"
        },
        "20": {
          "$description": "Alias for #CCE3DE.",
          "$value": "#CCE3DE"
        },
        "30": {
          "$description": "Alias for #5A998A.",
          "$value": "#5A998A"
        },
        "40": {
          "$description": "Alias for #3D8776.",
          "$value": "#3D8776"
        },
        "50": {
          "$description": "Alias for #2B6B5C.",
          "$value": "#2B6B5C"
        },
        "60": {
          "$description": "Alias for #24594D.",
          "$value": "#24594D"
        },
        "70": {
          "$description": "Alias for #1D473D.",
          "$value": "#1D473D"
        },
        "80": {
          "$description": "Alias for #004635.",
          "$value": "#004635"
        },
        "90": {
          "$description": "Alias for #143029.",
          "$value": "#143029"
        },
        "100": {
          "$description": "Alias for #00241C.",
          "$value": "#00241C"
        }
      },
      "orange": {
        "05": {
          "$description": "Alias for #FFFAF9.",
          "$value": "#FFFAF9"
        },
        "10": {
          "$description": "Alias for #FFEAE3.",
          "$value": "#FFEAE3"
        },
        "20": {
          "$description": "Alias for #FFC5B2.",
          "$value": "#FFC5B2"
        },
        "30": {
          "$description": "Alias for #FF7D51.",
          "$value": "#FF7D51"
        },
        "40": {
          "$description": "Alias for #FF5821.",
          "$value": "#FF5821"
        },
        "50": {
          "$description": "Alias for #BF5430.",
          "$value": "#BF5430"
        },
        "60": {
          "$description": "Alias for #BF3000.",
          "$value": "#BF3000"
        },
        "70": {
          "$description": "Alias for #8E2400.",
          "$value": "#8E2400"
        },
        "80": {
          "$description": "Alias for #5E1800.",
          "$value": "#5E1800"
        },
        "90": {
          "$description": "Alias for #471200.",
          "$value": "#471200"
        },
        "100": {
          "$description": "Alias for #2E0B00.",
          "$value": "#2E0B00"
        }
      },
      "pink": {
        "05": {
          "$description": "Alias for #FCF8FA.",
          "$value": "#FCF8FA"
        },
        "10": {
          "$description": "Alias for #EFD7E3.",
          "$value": "#EFD7E3"
        },
        "20": {
          "$description": "Alias for #E2B6CB.",
          "$value": "#E2B6CB"
        },
        "30": {
          "$description": "Alias for #D596B4.",
          "$value": "#D596B4"
        },
        "40": {
          "$description": "Alias for #BB5486.",
          "$value": "#BB5486"
        },
        "50": {
          "$description": "Alias for #A1406F.",
          "$value": "#A1406F"
        },
        "60": {
          "$description": "Alias for #803358.",
          "$value": "#803358"
        },
        "70": {
          "$description": "Alias for #732E4F.",
          "$value": "#732E4F"
        },
        "80": {
          "$description": "Alias for #5F2642.",
          "$value": "#5F2642"
        },
        "90": {
          "$description": "Alias for #3E192B.",
          "$value": "#3E192B"
        },
        "100": {
          "$description": "Alias for #330019.",
          "$value": "#330019"
        }
      },
      "purple": {
        "05": {
          "$description": "Alias for #F9F7FC.",
          "$value": "#F9F7FC"
        },
        "10": {
          "$description": "Alias for #F5F0FF.",
          "$value": "#F5F0FF"
        },
        "20": {
          "$description": "Alias for #DFD7EF.",
          "$value": "#DFD7EF"
        },
        "30": {
          "$description": "Alias for #CBBCE8.",
          "$value": "#CBBCE8"
        },
        "40": {
          "$description": "Alias for #AA95D4.",
          "$value": "#AA95D4"
        },
        "50": {
          "$description": "Alias for #9175C7.",
          "$value": "#9175C7"
        },
        "60": {
          "$description": "Alias for #7654BA.",
          "$value": "#7654BA"
        },
        "70": {
          "$description": "Alias for #60409F.",
          "$value": "#60409F"
        },
        "80": {
          "$description": "Alias for #4C337F.",
          "$value": "#4C337F"
        },
        "90": {
          "$description": "Alias for #39265E.",
          "$value": "#39265E"
        },
        "100": {
          "$description": "Alias for #25193D.",
          "$value": "#25193D"
        }
      },
      "red": {
        "05": {
          "$description": "Alias for #FBF3F4.",
          "$value": "#FBF3F4"
        },
        "10": {
          "$description": "Alias for #FFE5EA.",
          "$value": "#FFE5EA"
        },
        "20": {
          "$description": "Alias for #EFCDD3.",
          "$value": "#EFCDD3"
        },
        "30": {
          "$description": "Alias for #D78392.",
          "$value": "#D78392"
        },
        "40": {
          "$description": "Alias for #CB5D71.",
          "$value": "#CB5D71"
        },
        "50": {
          "$description": "Alias for #CB5D66.",
          "$value": "#CB5D66"
        },
        "60": {
          "$description": "Alias for #953042.",
          "$value": "#953042"
        },
        "70": {
          "$description": "Alias for #6F2432.",
          "$value": "#6F2432"
        },
        "80": {
          "$description": "Alias for #4A1821.",
          "$value": "#4A1821"
        },
        "90": {
          "$description": "Alias for #361118.",
          "$value": "#361118"
        },
        "100": {
          "$description": "Alias for #330009.",
          "$value": "#330009"
        }
      },
      "transparent": {
        "$description": "Alias for transparent.",
        "$value": "transparent"
      },
      "white": {
        "$description": "Alias for #FFFFFF.",
        "$value": "#FFFFFF"
      },
      "yellow": {
        "05": {
          "$description": "Alias for #FFFEF3.",
          "$value": "#FFFEF3"
        },
        "10": {
          "$description": "Alias for #F8F6E1.",
          "$value": "#F8F6E1"
        },
        "20": {
          "$description": "Alias for #D1CB92.",
          "$value": "#D1CB92"
        },
        "30": {
          "$description": "Alias for #DBD06A.",
          "$value": "#DBD06A"
        },
        "40": {
          "$description": "Alias for #B5A72C.",
          "$value": "#B5A72C"
        },
        "50": {
          "$description": "Alias for #8E8322.",
          "$value": "#8E8322"
        },
        "60": {
          "$description": "Alias for #998A00.",
          "$value": "#998A00"
        },
        "70": {
          "$description": "Alias for #665E19.",
          "$value": "#665E19"
        },
        "80": {
          "$description": "Alias for #403B0F.",
          "$value": "#403B0F"
        },
        "90": {
          "$description": "Alias for #332E00.",
          "$value": "#332E00"
        },
        "100": {
          "$description": "Alias for #2B2809.",
          "$value": "#2B2809"
        }
      }
    }
  }
}
